testwizard/commands_core/CommandBase.py
testwizard/commands_core/OkErrorCodeAndMessageResult.py
testwizard/commands_core/OkResult.py
testwizard/commands_core/ResultBase.py
testwizard/commands_core/SessionCommandBase.py
testwizard/commands_core/SimpleResult.py
testwizard/commands_core/__init__.py
testwizard.commands_core-3.8.1.dist-info/LICENSE.txt
testwizard.commands_core-3.8.1.dist-info/METADATA
testwizard.commands_core-3.8.1.dist-info/WHEEL
testwizard.commands_core-3.8.1.dist-info/top_level.txt
testwizard.commands_core-3.8.1.dist-info/RECORD
